[
    
    {
        "title":"Pdf 1 title here",
        "url":"https://codeforcore.com/demopdf.pdf",
        "subtitle":"Added date: sjd67"

    },
    {
        "title":"Pdf 2 title here",
        "url":"https://codeforcore.com/demopdf.pdf",
        "subtitle":"Added date: sjhfk"
    },
    {
        "title":"Pdf 3 title here",
        "url":"https://codeforcore.com/demopdf.pdf",
        "subtitle":"Added date: sjfkd"
    },
    {
        "title":"Pdf 4 title here",
        "url":"http://www.molrm.gov.np/uploads/files/मालपोत%20कार्यालय_28.pdf",
        "subtitle":"Added date: XXXX"
    },
    {
        "title":"Pdf 5 title here",
        "url":"https://codeforcore.com/demopdf.pdf",
        "subtitle":"Added date:xxx"
    }
]